ufal.morphodita-1.11.2.1.dist-info/RECORD
ufal.morphodita-1.11.2.1.dist-info/LICENSE
ufal.morphodita-1.11.2.1.dist-info/WHEEL
ufal.morphodita-1.11.2.1.dist-info/top_level.txt
ufal.morphodita-1.11.2.1.dist-info/METADATA
ufal/__init__.py
ufal/morphodita/__init__.pyi
ufal/morphodita/__init__.py
ufal/morphodita/_morphodita.cpython-311-darwin.so
ufal/morphodita/py.typed
