Metadata-Version: 2.1
Name: ufal.morphodita
Version: 1.11.2.1
Summary: Bindings to MorphoDiTa library
Home-page: https://ufal.mff.cuni.cz/morphodita
Author: Milan Straka
Author-email: straka@ufal.mff.cuni.cz
License: MPL 2.0
Classifier: Development Status :: 5 - Production/Stable
Classifier: License :: OSI Approved :: Mozilla Public License 2.0 (MPL 2.0)
Classifier: Programming Language :: C++
Classifier: Programming Language :: Python
Classifier: Programming Language :: Python :: 3
Classifier: Topic :: Software Development :: Libraries
License-File: LICENSE
